{
	"parent": "minecraft:recipes/root",
	"rewards": {
		"recipes": [
			"artisanat:stonecutting/cobblestone_brick_wall"
		]
	},
	"criteria": {
		"has_cobblestone": {
			"trigger": "minecraft:inventory_changed",
			"conditions": {
				"items": [
					{
						"items": ["minecraft:cobblestone"]
					}
				]
			}
		},
		"has_the_recipe": {
			"trigger": "minecraft:recipe_unlocked",
			"conditions": {
				"recipe": "artisanat:stonecutting/cobblestone_brick_wall"
			}
		}
	},
	"requirements": [
		[
			"has_cobblestone",
			"has_the_recipe"
		]
	]
}