{
	"parent": "minecraft:recipes/root",
	"rewards": {
		"recipes": [
			"nookbuild:stonecutting/prismarine_brick_paving_stairs"
		]
	},
	"criteria": {
		"has_prismarine_bricks": {
			"trigger": "minecraft:inventory_changed",
			"conditions": {
				"items": [
					{
						"item": "minecraft:prismarine_bricks"
					}
				]
			}
		},
		"has_the_recipe": {
			"trigger": "minecraft:recipe_unlocked",
			"conditions": {
				"recipe": "nookbuild:stonecutting/prismarine_brick_paving_stairs"
			}
		}
	},
	"requirements": [
		[
			"has_prismarine_bricks",
			"has_the_recipe"
		]
	]
}